{
  "_class": "artboard",
  "backgroundColor": {
    "_class": "color",
    "alpha": 1,
    "blue": 1,
    "green": 1,
    "red": 1
  },
  "booleanOperation": -1,
  "clippingMaskMode": 0,
  "do_objectID": "E19C381E-182E-4028-B447-B3F83A9341AC",
  "exportOptions": {
    "_class": "exportOptions",
    "exportFormats": [
    ],
    "includedLayerIds": [
    ],
    "layerOptions": 0,
    "shouldTrim": false
  },
  "frame": {
    "_class": "rect",
    "constrainProportions": false,
    "height": 5274,
    "width": 1440,
    "x": -645,
    "y": 20
  },
  "groupLayout": {
    "_class": "MSImmutableFreeformGroupLayout"
  },
  "hasBackgroundColor": true,
  "hasClickThrough": true,
  "hasClippingMask": false,
  "horizontalRulerData": {
    "_class": "rulerData",
    "base": 0,
    "guides": [
    ]
  },
  "includeBackgroundColorInExport": true,
  "includeInCloudUpload": true,
  "isFixedToViewport": false,
  "isFlippedHorizontal": false,
  "isFlippedVertical": false,
  "isFlowHome": false,
  "isLocked": false,
  "isVisible": true,
  "layerListExpandedType": 2,
  "layers": [
    {
      "class": "group",
      "id": "F7F2C35E-6881-4E58-BBA7-3D6E9D9440C8"
    },
    {
      "class": "symbolInstance",
      "id": "D3E72936-31FB-4F91-A9A4-426F1FF74A45"
    },
    {
      "class": "symbolInstance",
      "id": "9EB3692C-A21A-4845-82AF-B8A119A6FA91"
    },
    {
      "class": "symbolInstance",
      "id": "E44C99D3-47D0-4AF9-A34F-429B263F1784"
    },
    {
      "class": "symbolInstance",
      "id": "A4576E60-2521-4457-9BD2-B8CFD042BC12"
    },
    {
      "class": "symbolInstance",
      "id": "D1E56CEB-7210-4028-A775-ADC1BFF09AC1"
    },
    {
      "class": "symbolInstance",
      "id": "4C9C6FB2-C3BE-4DB2-9D60-9599BCA64CEA"
    },
    {
      "class": "text",
      "id": "3EE0F52E-06DA-44D0-9512-9DCC9B937AA1"
    },
    {
      "class": "text",
      "id": "B2123A42-9609-49B7-A400-EA1AE980FBBC"
    },
    {
      "class": "text",
      "id": "1014F85C-B2A5-409B-821F-2D8CB453D9A6"
    },
    {
      "class": "text",
      "id": "A2864AA9-30B4-43AB-90D2-5564C019563A"
    },
    {
      "class": "text",
      "id": "895418E7-46BF-494B-9465-64E1AB1EA914"
    },
    {
      "class": "text",
      "id": "6E2A8957-04DE-4BF6-8C85-9B6A86047427"
    },
    {
      "class": "text",
      "id": "4021E435-8A65-4364-9109-755E4BCE0A50"
    },
    {
      "class": "text",
      "id": "BBEB20AA-8960-44FA-8918-D4C4C388DFE3"
    },
    {
      "class": "text",
      "id": "ED95780E-0043-4678-8F9D-9E77E1E64EEC"
    },
    {
      "class": "text",
      "id": "D0B2D417-04CF-4403-A429-93140322A621"
    },
    {
      "class": "text",
      "id": "85ABB2AE-C269-41D8-A991-7FC1061CDC97"
    },
    {
      "class": "text",
      "id": "5ABD7857-AEDF-4CCE-8E2D-7A64B18CAABF"
    },
    {
      "class": "text",
      "id": "A8F553CC-AB2D-49EC-94EA-B8FBCF086FD2"
    },
    {
      "class": "text",
      "id": "B0037363-36EE-4FA6-99E5-2558CC1D4533"
    },
    {
      "class": "text",
      "id": "5A1F0680-E951-497C-935D-35204761882F"
    },
    {
      "class": "text",
      "id": "C6908A31-E0B3-47C9-9A68-BE417474D347"
    },
    {
      "class": "text",
      "id": "C743A5F0-BD1C-4606-AD6B-9D9273861676"
    },
    {
      "class": "symbolInstance",
      "id": "C5119DB2-E872-4167-B857-8711F86620C1"
    },
    {
      "class": "symbolInstance",
      "id": "6FB3C52E-AB83-4A41-8BB1-93FADA74DC5F"
    },
    {
      "class": "symbolInstance",
      "id": "D5DB515C-A40E-40D2-A0E0-AA737B2319CE"
    },
    {
      "class": "symbolInstance",
      "id": "BE2B2087-B60D-4162-84D1-64FF4FE64DD8"
    },
    {
      "class": "symbolInstance",
      "id": "E0656534-C4D6-4EBD-9C38-95E32474ECEF"
    },
    {
      "class": "symbolInstance",
      "id": "7FDE6406-682C-411A-9898-2FCA915C54FC"
    },
    {
      "class": "symbolInstance",
      "id": "E2242DBB-15CD-4548-BD35-AE40F35C9DC1"
    },
    {
      "class": "symbolInstance",
      "id": "468FA7F4-C66F-4E7A-BBAB-F061A104A9FC"
    },
    {
      "class": "group",
      "id": "292A8ADD-BA96-4895-8507-B276E920AAE3"
    },
    {
      "class": "symbolInstance",
      "id": "0B69E45A-E90A-4258-BBEA-4079B7F5CB9C"
    }
  ],
  "name": "自增组件",
  "nameIsFixed": true,
  "presetDictionary": {
    "allowResizedMatching": 0,
    "height": 1024,
    "name": "桌面端 HD",
    "offersLandscapeVariant": 0,
    "width": 1440
  },
  "resizesContent": false,
  "resizingConstraint": 63,
  "resizingType": 0,
  "rotation": 0,
  "shouldBreakMaskChain": true,
  "style": {
    "_class": "style",
    "blur": {
      "_class": "blur",
      "center": "{0.5, 0.5}",
      "isEnabled": false,
      "motionAngle": 0,
      "radius": 10,
      "saturation": 1,
      "type": 0
    },
    "borderOptions": {
      "_class": "borderOptions",
      "dashPattern": [
      ],
      "isEnabled": true,
      "lineCapStyle": 0,
      "lineJoinStyle": 0
    },
    "borders": [
    ],
    "colorControls": {
      "_class": "colorControls",
      "brightness": 0,
      "contrast": 1,
      "hue": 0,
      "isEnabled": false,
      "saturation": 1
    },
    "contextSettings": {
      "_class": "graphicsContextSettings",
      "blendMode": 0,
      "opacity": 1
    },
    "do_objectID": "2FB68501-769F-434B-B00F-8A3B124D69F9",
    "endMarkerType": 0,
    "fills": [
    ],
    "innerShadows": [
    ],
    "miterLimit": 10,
    "shadows": [
    ],
    "startMarkerType": 0,
    "windingRule": 1
  },
  "verticalRulerData": {
    "_class": "rulerData",
    "base": 0,
    "guides": [
    ]
  }
}