{
  "_class": "symbolInstance",
  "booleanOperation": -1,
  "clippingMaskMode": 0,
  "do_objectID": "BEB6D0B8-E299-4AD9-95C1-5A2E10C810C5",
  "exportOptions": {
    "_class": "exportOptions",
    "exportFormats": [
    ],
    "includedLayerIds": [
    ],
    "layerOptions": 0,
    "shouldTrim": false
  },
  "frame": {
    "_class": "rect",
    "constrainProportions": false,
    "height": 32,
    "width": 32,
    "x": 1251,
    "y": 154
  },
  "hasClippingMask": false,
  "horizontalSpacing": 0,
  "isFixedToViewport": false,
  "isFlippedHorizontal": false,
  "isFlippedVertical": false,
  "isLocked": false,
  "isVisible": true,
  "layerListExpandedType": 0,
  "name": "Buttons（按钮）/大号/主按钮/纯文本/00 默认备份 9",
  "nameIsFixed": false,
  "overrideValues": [
    {
      "_class": "overrideValue",
      "overrideName": "91AD9F0A-1069-4769-BEE7-4BE381064C50_symbolID",
      "value": "A8AE12B9-ACA1-4A7B-BDC6-A818B19F9EE3"
    }
  ],
  "resizingConstraint": 63,
  "resizingType": 0,
  "rotation": 0,
  "scale": 1,
  "shouldBreakMaskChain": false,
  "style": {
    "_class": "style",
    "blur": {
      "_class": "blur",
      "center": "{0.5, 0.5}",
      "isEnabled": false,
      "motionAngle": 0,
      "radius": 10,
      "saturation": 1,
      "type": 0
    },
    "borderOptions": {
      "_class": "borderOptions",
      "dashPattern": [
      ],
      "isEnabled": true,
      "lineCapStyle": 0,
      "lineJoinStyle": 0
    },
    "borders": [
    ],
    "colorControls": {
      "_class": "colorControls",
      "brightness": 0,
      "contrast": 1,
      "hue": 0,
      "isEnabled": false,
      "saturation": 1
    },
    "contextSettings": {
      "_class": "graphicsContextSettings",
      "blendMode": 0,
      "opacity": 1
    },
    "do_objectID": "6111E498-374B-4C62-AC0D-269C738C1E97",
    "endMarkerType": 0,
    "fills": [
    ],
    "innerShadows": [
    ],
    "miterLimit": 10,
    "shadows": [
    ],
    "startMarkerType": 0,
    "windingRule": 1
  },
  "symbolID": "61CFAE3A-FE6A-4848-80A7-E668368E0F9C",
  "verticalSpacing": 0
}