{
  "_class": "group",
  "booleanOperation": -1,
  "clippingMaskMode": 0,
  "do_objectID": "4B963946-75C2-49FE-8A29-FCE1EAF9AAAA",
  "exportOptions": {
    "_class": "exportOptions",
    "exportFormats": [
    ],
    "includedLayerIds": [
    ],
    "layerOptions": 0,
    "shouldTrim": false
  },
  "frame": {
    "_class": "rect",
    "constrainProportions": false,
    "height": 1116,
    "width": 1200,
    "x": 120,
    "y": 978
  },
  "groupLayout": {
    "_class": "MSImmutableFreeformGroupLayout"
  },
  "hasClickThrough": false,
  "hasClippingMask": false,
  "isFixedToViewport": false,
  "isFlippedHorizontal": false,
  "isFlippedVertical": false,
  "isLocked": false,
  "isVisible": true,
  "layerListExpandedType": 2,
  "layers": [
    {
      "class": "group",
      "id": "26F11928-0035-4503-AAAF-189A726C88BB"
    },
    {
      "class": "group",
      "id": "47A98854-C5CF-476C-9796-1FFFEA51599B"
    },
    {
      "class": "group",
      "id": "CEEA61EA-D3C2-4689-88B3-D93D53DF2E2C"
    },
    {
      "class": "group",
      "id": "EE049218-43B5-4148-9AC7-F8F87C938666"
    },
    {
      "class": "group",
      "id": "1F9847E4-6991-4C2C-B1F1-B02EE2D0ACE2"
    },
    {
      "class": "group",
      "id": "A5A11B9F-0A45-4BD3-BB06-5BC4FCBF8BBF"
    },
    {
      "class": "group",
      "id": "D1860BF6-E0C7-42DD-A118-438BFB5BC60C"
    },
    {
      "class": "text",
      "id": "BE1B9AD0-4505-4B9D-9361-E6833B122CD9"
    }
  ],
  "name": "图例备份",
  "nameIsFixed": true,
  "resizingConstraint": 9,
  "resizingType": 0,
  "rotation": 0,
  "shouldBreakMaskChain": false,
  "style": {
    "_class": "style",
    "blur": {
      "_class": "blur",
      "center": "{0.5, 0.5}",
      "isEnabled": false,
      "motionAngle": 0,
      "radius": 10,
      "saturation": 1,
      "type": 0
    },
    "borderOptions": {
      "_class": "borderOptions",
      "dashPattern": [
      ],
      "isEnabled": true,
      "lineCapStyle": 0,
      "lineJoinStyle": 0
    },
    "borders": [
    ],
    "colorControls": {
      "_class": "colorControls",
      "brightness": 0,
      "contrast": 1,
      "hue": 0,
      "isEnabled": true,
      "saturation": 1
    },
    "contextSettings": {
      "_class": "graphicsContextSettings",
      "blendMode": 0,
      "opacity": 1
    },
    "do_objectID": "FB508ECF-0598-4F0B-9157-3CA4D8B19EC1",
    "endMarkerType": 0,
    "fills": [
    ],
    "innerShadows": [
    ],
    "miterLimit": 10,
    "shadows": [
    ],
    "startMarkerType": 0,
    "windingRule": 1
  }
}